caishengxiang/__init__.py
caishengxiang/clients/__init__.py
caishengxiang/clients/gpt.py
caishengxiang/clients/gptV3.py
caishengxiang/libs/__init__.py
caishengxiang/libs/zipstream/__init__.py
caishengxiang/libs/zipstream/aiozipstream.py
caishengxiang/libs/zipstream/consts.py
caishengxiang/libs/zipstream/zipstream.py
caishengxiang/logger/__init__.py
caishengxiang/logger/simple_log.py
caishengxiang/ops/__init__.py
caishengxiang/ops/pssh_tool.py
caishengxiang/study/__init__.py
caishengxiang/study/classs.py
caishengxiang/study/dicts.py
caishengxiang/study/regulars/__init__.py
caishengxiang/study/regulars/finds.py
caishengxiang/utils/__init__.py
caishengxiang/utils/ddns/__init__.py
caishengxiang/utils/ddns/update_ipv6.py
caishengxiang/utils/draw_tools/__init__.py
caishengxiang/utils/draw_tools/echarts_draw.py
caishengxiang/utils/file_tools/__init__.py
caishengxiang/utils/file_tools/chmod.py
caishengxiang/utils/file_tools/file.py
caishengxiang/utils/file_tools/zip.py
caishengxiang/utils/monitor_tools/__init__.py
caishengxiang/utils/monitor_tools/monitor.py
caishengxiang/utils/monitor_tools/monitor_server.py
caishengxiang/utils/pandas_tools/__init__.py
caishengxiang/utils/pandas_tools/example.py
caishengxiang/utils/str_tools/__init__.py
caishengxiang/utils/time_tools/__init__.py
caishengxiang/utils/time_tools/c_date.py
caishengxiang/utils/time_tools/c_dateutil.py
caishengxiang/utils/time_tools/time_type.py
caishengxiang-0.2.2.dist-info/LICENSE
caishengxiang-0.2.2.dist-info/METADATA
caishengxiang-0.2.2.dist-info/WHEEL
caishengxiang-0.2.2.dist-info/entry_points.txt
caishengxiang-0.2.2.dist-info/top_level.txt
caishengxiang-0.2.2.dist-info/RECORD
