Metadata-Version: 2.1
Name: caishengxiang
Version: 0.2.2
Author-email: caishengxiang <wancheng3833@163.com>
License: MIT License
Classifier: Programming Language :: Python :: 3
Classifier: License :: OSI Approved :: MIT License
Classifier: Operating System :: OS Independent
Requires-Python: >=3.8
License-File: LICENSE
Requires-Dist: setuptools >=65.3.0
Requires-Dist: wheel >=0.37.1
Requires-Dist: requests
